{
  "name": "YeAter Alicha Kik Wot (Ethiopian Mild Yellow Split Pea Stew) Recipe",
  "category": "Untested",
  "description": "",
  "prepTime": "Prep time",
  "cookTime": "Total time",
  "image": "",
  "ingredients": [
    "1 cup split peas",
    "1 cup onion (minced)",
    "1 tbsp ginger (minced)",
    "1 tbsp garlic (minced)",
    "1 tsp Alicha Kimem (Afrenje)",
    "1 tsp Netch Azmud (Caraway Seed)",
    "1 tsp of Turmeric",
    "½ cup oil",
    "3 cups water",
    "Salt (to taste)"
  ],
  "instructions": [
    "Thoroughly wash the split peas using hot water until they’re clean enough that the water they are placed is clear.",
    "Soak the split peas in water until they are fully rehydrated. Then strain the remaining water for approx. 20 min.",
    "Cook the onions for 10 min. in water over medium heat until the onions are thoroughly cooked and transparent.",
    "Add some water, then the minced ginger, and stir for about 3 min. until the mixture reaches a paste-like in texture.",
    "Add the minced garlic and the oil, and mix well.",
    "Pour in some water now and again as the sauce starts to thicken while stirring gently.",
    "Now, add the split peas slowly along with some water, making sure the split peas are not burnt. Then stir the mix for 2 min.",
    "Pour in more water till the split peas are submerged completely, and continue stirring for approx. 8 min. when the split peas become soft.",
    "Then add the Tumeric and Alicha Kimem and continue cooking for 1 min. till the mixture becomes fragrant.",
    "Lower the heat and simmer the mixture for about 5 min. and add the Netch Azmud while stirring.",
    "Finally, turn the heat off, add some salt, and serve your Alicha Kik Wot along with Injera."
  ],
  "dateAdded": "2025-12-05T17:17:23.646Z"
}